<?xml version="1.0" encoding="UTF-8"?>
<objects serializationModel="Studio.02.01.00">
	<object class="EncodingSetting" id="{294a92e0-ef74-4462-ba37-1ec3906b81d0}">
		<property name="encodingFormat">
			<value>3</value>
		</property>
		<property name="quality">
			<value>30</value>
		</property>
		<property name="sampleRate">
			<value>40000</value>
		</property>
		<property name="loadingMode">
			<value>2</value>
		</property>
		<relationship name="platform">
			<destination>{180d81b9-f37d-43d2-a142-83edaf994a67}</destination>
		</relationship>
		<relationship name="encodable">
			<destination>{7a7069b9-35dc-4212-8a7d-8728eb69c928}</destination>
		</relationship>
	</object>
</objects>
