<?xml version="1.0" encoding="UTF-8"?>
<objects serializationModel="Studio.02.01.00">
	<object class="EncodingSetting" id="{6692f1dd-5c27-4351-9dcd-721ef2d1a851}">
		<property name="encodingFormat">
			<value>3</value>
		</property>
		<property name="quality">
			<value>20</value>
		</property>
		<property name="sampleRate">
			<value>30000</value>
		</property>
		<relationship name="platform">
			<destination>{180d81b9-f37d-43d2-a142-83edaf994a67}</destination>
		</relationship>
		<relationship name="encodable">
			<destination>{24946a28-9c11-43b8-86ac-5d9f640ddbc9}</destination>
		</relationship>
	</object>
</objects>
