<?xml version="1.0" encoding="UTF-8"?>
<objects serializationModel="Studio.02.01.00">
	<object class="EncodingSetting" id="{bd7ba526-09f1-4b79-b34f-c83dd3fdf605}">
		<property name="encodingFormat">
			<value>3</value>
		</property>
		<property name="quality">
			<value>30</value>
		</property>
		<property name="sampleRate">
			<value>35000</value>
		</property>
		<property name="loadingMode">
			<value>2</value>
		</property>
		<relationship name="platform">
			<destination>{180d81b9-f37d-43d2-a142-83edaf994a67}</destination>
		</relationship>
		<relationship name="encodable">
			<destination>{36f398f3-a6f4-48ec-b61e-0a5cdd8315e7}</destination>
		</relationship>
	</object>
</objects>
